streamlit_custome_css/__init__.py
streamlit_custome_css/leo.py
streamlit_custome_css-1.0.dist-info/LICENSE.txt
streamlit_custome_css-1.0.dist-info/METADATA
streamlit_custome_css-1.0.dist-info/WHEEL
streamlit_custome_css-1.0.dist-info/top_level.txt
streamlit_custome_css-1.0.dist-info/RECORD
