Metadata-Version: 2.1
Name: streamlit-custome-css
Version: 1.0
Summary: streamlit custome css function and sending mail services , text to speech 
Home-page: UNKNOWN
Author: leo joel roys
Author-email: joelroys637@gmail.com
License: MIT
Project-URL: Source Repository, https://github.com/Joelroys637
Platform: UNKNOWN
Requires-Dist: streamlit
